django_varlet-0.2.3.dist-info/DESCRIPTION.rst
django_varlet-0.2.3.dist-info/LICENSE.txt
django_varlet-0.2.3.dist-info/METADATA
django_varlet-0.2.3.dist-info/RECORD
django_varlet-0.2.3.dist-info/WHEEL
django_varlet-0.2.3.dist-info/metadata.json
django_varlet-0.2.3.dist-info/top_level.txt
varlet/__init__.py
varlet/admin.py
varlet/apps.py
varlet/models.py
varlet/search_indexes.py
varlet/serializers.py
varlet/sitemaps.py
varlet/urls.py
varlet/views.py
varlet/contrib/__init__.py
varlet/contrib/haystack_urls.py
varlet/contrib/haystack_views.py
varlet/migrations/0001_initial.py
varlet/migrations/__init__.py
varlet/static/varlet/riot.min.js
varlet/static/varlet/urlpath-autocomplete.css
varlet/static/varlet/urlpath-autocomplete.js
varlet/static/varlet/urlpath-autocomplete.tag
varlet/templates/django/forms/widgets/urlpath-autocomplete.html
varlet/templates/search/indexes/varlet/page_text.txt
varlet/templatetags/__init__.py
varlet/templatetags/page_tags.py
varlet/tests/__init__.py
varlet/tests/test_admin.py
varlet/tests/test_files.py
varlet/tests/test_model_cleaning.py
varlet/tests/test_sitemaps.py
varlet/tests/test_templatetag.py
varlet/tests/test_views.py
varlet/tests/templates/varlet/pages/layouts/test_template.html
varlet/tests/templates/varlet/pages/layouts/test_template_2.html
