Metadata-Version: 2.0
Name: django-varlet
Version: 0.2.3
Summary: URLs which render specified templates, controlled via models and the admin
Home-page: https://github.com/kezabelle/django-varlet
Author: Keryn Knight
Author-email: django-varlet@kerynknight.com
License: BSD License
Keywords: django varlet url template
Platform: UNKNOWN
Classifier: Development Status :: 3 - Alpha
Classifier: Intended Audience :: Developers
Classifier: License :: OSI Approved :: BSD License
Classifier: Natural Language :: English
Classifier: Programming Language :: Python :: 2
Classifier: Programming Language :: Python :: 2.7
Classifier: Programming Language :: Python :: 3
Classifier: Programming Language :: Python :: 3.3
Classifier: Programming Language :: Python :: 3.4
Classifier: Programming Language :: Python :: 3.5
Classifier: Framework :: Django
Classifier: Framework :: Django :: 1.11
Classifier: Framework :: Django :: 1.10
Classifier: Framework :: Django :: 1.8
Classifier: Framework :: Django :: 1.9
Requires-Dist: Django (>=1.11)
Requires-Dist: djangorestframework (>=3.6)
Requires-Dist: swapper (>=1.0.0)
Requires-Dist: django-templateselector (>=0.2.3)
